{
	"id": {
		"national": 438,
		"mountain_kalos_xy": 129,
		"alola_usum": 37,
		"galar_swsh": 252,
		"sinnoh_bdsp": 92,
		"hisui_legarc": 123,
		"paldea_sv": 87,
		"kitakami_sv": 83
	},
	"name": {
		"en": "Bonsly",
		"jp": "ウソハチ",
		"chs": "",
		"cht": ""
	},
	"baby": true,
	"default": {
		"desc": "Bonsai Pokémon",
		"type_id": [8, -1],
		"type": ["rock"],
		"abilities": {
			"ability_1": "Sturdy",
			"ability_2": "Rock Head",
			"hidden_ability": "Rattled",
			"terastal_ability": false
		}
	}
}